{
    "data": [
        {
            "_id": "659d355ccd960f131d88d89a",
            "CH_SYMBOL": "ICICIBANK",
            "CH_SERIES": "EQ",
            "CH_MARKET_TYPE": "N",
            "CH_TRADE_HIGH_PRICE": 995,
            "CH_TRADE_LOW_PRICE": 975.4,
            "CH_OPENING_PRICE": 986.25,
            "CH_CLOSING_PRICE": 979.75,
            "CH_LAST_TRADED_PRICE": 978,
            "CH_PREVIOUS_CLS_PRICE": 982,
            "CH_TOT_TRADED_QTY": 14660414,
            "CH_TOT_TRADED_VAL": 14434925887.7,
            "CH_52WEEK_HIGH_PRICE": 1043.7,
            "CH_52WEEK_LOW_PRICE": 796,
            "CH_TOTAL_TRADES": 202344,
            "CH_ISIN": "INE090A01021",
            "CH_TIMESTAMP": "2024-01-09",
            "TIMESTAMP": "2024-01-08T18:30:00.000Z",
            "createdAt": "2024-01-09T12:00:28.986Z",
            "updatedAt": "2024-01-09T12:00:28.986Z",
            "__v": 0,
            "COP_DELIV_QTY": 5515197,
            "COP_DELIV_PERC": 37.62,
            "VWAP": 984.62,
            "mTIMESTAMP": "09-Jan-2024"
        },
        {
            "_id": "659e86dd3207e4f9f5290be6",
            "CH_SYMBOL": "ICICIBANK",
            "CH_SERIES": "EQ",
            "CH_MARKET_TYPE": "N",
            "CH_TRADE_HIGH_PRICE": 994.95,
            "CH_TRADE_LOW_PRICE": 974.3,
            "CH_OPENING_PRICE": 974.3,
            "CH_CLOSING_PRICE": 993.05,
            "CH_LAST_TRADED_PRICE": 992.5,
            "CH_PREVIOUS_CLS_PRICE": 979.75,
            "CH_TOT_TRADED_QTY": 9409181,
            "CH_TOT_TRADED_VAL": 9308354597.1,
            "CH_52WEEK_HIGH_PRICE": 1043.7,
            "CH_52WEEK_LOW_PRICE": 796,
            "CH_TOTAL_TRADES": 183064,
            "CH_ISIN": "INE090A01021",
            "CH_TIMESTAMP": "2024-01-10",
            "TIMESTAMP": "2024-01-09T18:30:00.000Z",
            "createdAt": "2024-01-10T12:00:29.165Z",
            "updatedAt": "2024-01-10T12:00:29.165Z",
            "__v": 0,
            "COP_DELIV_QTY": 5749186,
            "COP_DELIV_PERC": 61.1,
            "VWAP": 989.28,
            "mTIMESTAMP": "10-Jan-2024"
        },
        {
            "_id": "659fd85dea2187a7f76e7f51",
            "CH_SYMBOL": "ICICIBANK",
            "CH_SERIES": "EQ",
            "CH_MARKET_TYPE": "N",
            "CH_TRADE_HIGH_PRICE": 998.5,
            "CH_TRADE_LOW_PRICE": 986.85,
            "CH_OPENING_PRICE": 995.3,
            "CH_CLOSING_PRICE": 991.15,
            "CH_LAST_TRADED_PRICE": 990.4,
            "CH_PREVIOUS_CLS_PRICE": 993.05,
            "CH_TOT_TRADED_QTY": 6451345,
            "CH_TOT_TRADED_VAL": 6395101765.1,
            "CH_52WEEK_HIGH_PRICE": 1043.7,
            "CH_52WEEK_LOW_PRICE": 796,
            "CH_TOTAL_TRADES": 205605,
            "CH_ISIN": "INE090A01021",
            "CH_TIMESTAMP": "2024-01-11",
            "TIMESTAMP": "2024-01-10T18:30:00.000Z",
            "createdAt": "2024-01-11T12:00:29.179Z",
            "updatedAt": "2024-01-11T12:00:29.179Z",
            "__v": 0,
            "COP_DELIV_QTY": 3996181,
            "COP_DELIV_PERC": 61.94,
            "VWAP": 991.28,
            "mTIMESTAMP": "11-Jan-2024"
        },
        {
            "_id": "65a129fe40ce9096768bce20",
            "CH_SYMBOL": "ICICIBANK",
            "CH_SERIES": "EQ",
            "CH_MARKET_TYPE": "N",
            "CH_TRADE_HIGH_PRICE": 1008.7,
            "CH_TRADE_LOW_PRICE": 991.75,
            "CH_OPENING_PRICE": 994.8,
            "CH_CLOSING_PRICE": 1003.5,
            "CH_LAST_TRADED_PRICE": 1001.95,
            "CH_PREVIOUS_CLS_PRICE": 991.15,
            "CH_TOT_TRADED_QTY": 12255743,
            "CH_TOT_TRADED_VAL": 12290375605.85,
            "CH_52WEEK_HIGH_PRICE": 1043.7,
            "CH_52WEEK_LOW_PRICE": 796,
            "CH_TOTAL_TRADES": 255004,
            "CH_ISIN": "INE090A01021",
            "CH_TIMESTAMP": "2024-01-12",
            "TIMESTAMP": "2024-01-11T18:30:00.000Z",
            "createdAt": "2024-01-12T12:01:02.169Z",
            "updatedAt": "2024-01-12T12:01:02.169Z",
            "__v": 0,
            "COP_DELIV_QTY": 8277142,
            "COP_DELIV_PERC": 67.54,
            "VWAP": 1002.83,
            "mTIMESTAMP": "12-Jan-2024"
        },
        {
            "_id": "65a523116b1be37ce45ad64b",
            "CH_SYMBOL": "ICICIBANK",
            "CH_SERIES": "EQ",
            "CH_MARKET_TYPE": "N",
            "CH_TRADE_HIGH_PRICE": 1011.65,
            "CH_TRADE_LOW_PRICE": 999.25,
            "CH_OPENING_PRICE": 1003.5,
            "CH_CLOSING_PRICE": 1009.85,
            "CH_LAST_TRADED_PRICE": 1010,
            "CH_PREVIOUS_CLS_PRICE": 1003.5,
            "CH_TOT_TRADED_QTY": 12388044,
            "CH_TOT_TRADED_VAL": 12475200079.75,
            "CH_52WEEK_HIGH_PRICE": 1043.7,
            "CH_52WEEK_LOW_PRICE": 796,
            "CH_TOTAL_TRADES": 339028,
            "CH_ISIN": "INE090A01021",
            "CH_TIMESTAMP": "2024-01-15",
            "TIMESTAMP": "2024-01-14T18:30:00.000Z",
            "createdAt": "2024-01-15T12:20:33.962Z",
            "updatedAt": "2024-01-15T12:20:33.962Z",
            "__v": 0,
            "COP_DELIV_QTY": 7485540,
            "COP_DELIV_PERC": 60.43,
            "VWAP": 1007.04,
            "mTIMESTAMP": "15-Jan-2024"
        },
        {
            "_id": "65a66fe2b8ccbcfd4c2a0c98",
            "CH_SYMBOL": "ICICIBANK",
            "CH_SERIES": "EQ",
            "CH_MARKET_TYPE": "N",
            "CH_TRADE_HIGH_PRICE": 1015.8,
            "CH_TRADE_LOW_PRICE": 1004.6,
            "CH_OPENING_PRICE": 1006.1,
            "CH_CLOSING_PRICE": 1009.05,
            "CH_LAST_TRADED_PRICE": 1007.65,
            "CH_PREVIOUS_CLS_PRICE": 1009.85,
            "CH_TOT_TRADED_QTY": 11505126,
            "CH_TOT_TRADED_VAL": 11626570821.35,
            "CH_52WEEK_HIGH_PRICE": 1043.7,
            "CH_52WEEK_LOW_PRICE": 796,
            "CH_TOTAL_TRADES": 286201,
            "CH_ISIN": "INE090A01021",
            "CH_TIMESTAMP": "2024-01-16",
            "TIMESTAMP": "2024-01-15T18:30:00.000Z",
            "createdAt": "2024-01-16T12:00:34.674Z",
            "updatedAt": "2024-01-16T12:00:34.674Z",
            "__v": 0,
            "COP_DELIV_QTY": 6625571,
            "COP_DELIV_PERC": 57.59,
            "VWAP": 1010.56,
            "mTIMESTAMP": "16-Jan-2024"
        },
        {
            "_id": "65a7c17e0a0ab9503507076e",
            "CH_SYMBOL": "ICICIBANK",
            "CH_SERIES": "EQ",
            "CH_MARKET_TYPE": "N",
            "CH_TRADE_HIGH_PRICE": 1007.8,
            "CH_TRADE_LOW_PRICE": 976.75,
            "CH_OPENING_PRICE": 987.9,
            "CH_CLOSING_PRICE": 981.75,
            "CH_LAST_TRADED_PRICE": 979.5,
            "CH_PREVIOUS_CLS_PRICE": 1009.05,
            "CH_TOT_TRADED_QTY": 41914771,
            "CH_TOT_TRADED_VAL": 41483325173.95,
            "CH_52WEEK_HIGH_PRICE": 1043.7,
            "CH_52WEEK_LOW_PRICE": 796,
            "CH_TOTAL_TRADES": 580135,
            "CH_ISIN": "INE090A01021",
            "CH_TIMESTAMP": "2024-01-17",
            "TIMESTAMP": "2024-01-16T18:30:00.000Z",
            "createdAt": "2024-01-17T12:01:02.686Z",
            "updatedAt": "2024-01-17T12:01:02.686Z",
            "__v": 0,
            "COP_DELIV_QTY": 17595246,
            "COP_DELIV_PERC": 41.98,
            "VWAP": 989.71,
            "mTIMESTAMP": "17-Jan-2024"
        },
        {
            "_id": "65a912dd1ba6ed2ab4d2265d",
            "CH_SYMBOL": "ICICIBANK",
            "CH_SERIES": "EQ",
            "CH_MARKET_TYPE": "N",
            "CH_TRADE_HIGH_PRICE": 994.3,
            "CH_TRADE_LOW_PRICE": 970.15,
            "CH_OPENING_PRICE": 973.95,
            "CH_CLOSING_PRICE": 986.35,
            "CH_LAST_TRADED_PRICE": 987.5,
            "CH_PREVIOUS_CLS_PRICE": 981.75,
            "CH_TOT_TRADED_QTY": 17902484,
            "CH_TOT_TRADED_VAL": 17626126346.95,
            "CH_52WEEK_HIGH_PRICE": 1043.7,
            "CH_52WEEK_LOW_PRICE": 796,
            "CH_TOTAL_TRADES": 405442,
            "CH_ISIN": "INE090A01021",
            "CH_TIMESTAMP": "2024-01-18",
            "TIMESTAMP": "2024-01-17T18:30:00.000Z",
            "createdAt": "2024-01-18T12:00:29.420Z",
            "updatedAt": "2024-01-18T12:00:29.420Z",
            "__v": 0,
            "COP_DELIV_QTY": 11114591,
            "COP_DELIV_PERC": 62.08,
            "VWAP": 984.56,
            "mTIMESTAMP": "18-Jan-2024"
        },
        {
            "_id": "65aa64baf173ca68878c2820",
            "CH_SYMBOL": "ICICIBANK",
            "CH_SERIES": "EQ",
            "CH_MARKET_TYPE": "N",
            "CH_TRADE_HIGH_PRICE": 1010.9,
            "CH_TRADE_LOW_PRICE": 987.55,
            "CH_OPENING_PRICE": 991.3,
            "CH_CLOSING_PRICE": 999.2,
            "CH_LAST_TRADED_PRICE": 1000,
            "CH_PREVIOUS_CLS_PRICE": 986.35,
            "CH_TOT_TRADED_QTY": 23271148,
            "CH_TOT_TRADED_VAL": 23332513523.6,
            "CH_52WEEK_HIGH_PRICE": 1043.7,
            "CH_52WEEK_LOW_PRICE": 796,
            "CH_TOTAL_TRADES": 373845,
            "CH_ISIN": "INE090A01021",
            "CH_TIMESTAMP": "2024-01-19",
            "TIMESTAMP": "2024-01-18T18:30:00.000Z",
            "createdAt": "2024-01-19T12:02:02.368Z",
            "updatedAt": "2024-01-19T12:02:02.368Z",
            "__v": 0,
            "COP_DELIV_QTY": 16874233,
            "COP_DELIV_PERC": 72.51,
            "VWAP": 1002.64,
            "mTIMESTAMP": "19-Jan-2024"
        },
        {
            "_id": "65abe14231f9ebde19837154",
            "CH_SYMBOL": "ICICIBANK",
            "CH_SERIES": "EQ",
            "CH_MARKET_TYPE": "N",
            "CH_TRADE_HIGH_PRICE": 1014.7,
            "CH_TRADE_LOW_PRICE": 995.3,
            "CH_OPENING_PRICE": 1005.95,
            "CH_CLOSING_PRICE": 1008.7,
            "CH_LAST_TRADED_PRICE": 1011.5,
            "CH_PREVIOUS_CLS_PRICE": 999.2,
            "CH_TOT_TRADED_QTY": 8788873,
            "CH_TOT_TRADED_VAL": 8834323616.8,
            "CH_52WEEK_HIGH_PRICE": 1043.7,
            "CH_52WEEK_LOW_PRICE": 796,
            "CH_TOTAL_TRADES": 172248,
            "CH_ISIN": "INE090A01021",
            "CH_TIMESTAMP": "2024-01-20",
            "TIMESTAMP": "2024-01-19T18:30:00.000Z",
            "createdAt": "2024-01-20T15:05:38.386Z",
            "updatedAt": "2024-01-20T15:05:38.386Z",
            "__v": 0,
            "COP_DELIV_QTY": 1752682,
            "COP_DELIV_PERC": 19.94,
            "VWAP": 1005.17,
            "mTIMESTAMP": "20-Jan-2024"
        },
        {
            "_id": "65afaa7df8104146405a1cb0",
            "CH_SYMBOL": "ICICIBANK",
            "CH_SERIES": "EQ",
            "CH_MARKET_TYPE": "N",
            "CH_TRADE_HIGH_PRICE": 1059.4,
            "CH_TRADE_LOW_PRICE": 1021.2,
            "CH_OPENING_PRICE": 1059.1,
            "CH_CLOSING_PRICE": 1029.05,
            "CH_LAST_TRADED_PRICE": 1027.9,
            "CH_PREVIOUS_CLS_PRICE": 1008.7,
            "CH_TOT_TRADED_QTY": 50797448,
            "CH_TOT_TRADED_VAL": 52616782751.05,
            "CH_52WEEK_HIGH_PRICE": 1059.4,
            "CH_52WEEK_LOW_PRICE": 796,
            "CH_TOTAL_TRADES": 669065,
            "CH_ISIN": "INE090A01021",
            "CH_TIMESTAMP": "2024-01-23",
            "TIMESTAMP": "2024-01-22T18:30:00.000Z",
            "createdAt": "2024-01-23T12:01:01.932Z",
            "updatedAt": "2024-01-23T12:01:01.932Z",
            "__v": 0,
            "COP_DELIV_QTY": 31661624,
            "COP_DELIV_PERC": 62.33,
            "VWAP": 1035.82,
            "mTIMESTAMP": "23-Jan-2024"
        },
        {
            "_id": "65b0fbde16e02b4d67f83cbf",
            "CH_SYMBOL": "ICICIBANK",
            "CH_SERIES": "EQ",
            "CH_MARKET_TYPE": "N",
            "CH_TRADE_HIGH_PRICE": 1035.95,
            "CH_TRADE_LOW_PRICE": 996.65,
            "CH_OPENING_PRICE": 1029.45,
            "CH_CLOSING_PRICE": 999.2,
            "CH_LAST_TRADED_PRICE": 998.3,
            "CH_PREVIOUS_CLS_PRICE": 1029.05,
            "CH_TOT_TRADED_QTY": 34578943,
            "CH_TOT_TRADED_VAL": 34786249969.95,
            "CH_52WEEK_HIGH_PRICE": 1059.4,
            "CH_52WEEK_LOW_PRICE": 796,
            "CH_TOTAL_TRADES": 341150,
            "CH_ISIN": "INE090A01021",
            "CH_TIMESTAMP": "2024-01-24",
            "TIMESTAMP": "2024-01-23T18:30:00.000Z",
            "createdAt": "2024-01-24T12:00:30.683Z",
            "updatedAt": "2024-01-24T12:00:30.683Z",
            "__v": 0,
            "COP_DELIV_QTY": 23014320,
            "COP_DELIV_PERC": 66.56,
            "VWAP": 1006,
            "mTIMESTAMP": "24-Jan-2024"
        },
        {
            "_id": "65b24d5fed15adb98be7d423",
            "CH_SYMBOL": "ICICIBANK",
            "CH_SERIES": "EQ",
            "CH_MARKET_TYPE": "N",
            "CH_TRADE_HIGH_PRICE": 1015.1,
            "CH_TRADE_LOW_PRICE": 988.15,
            "CH_OPENING_PRICE": 998.4,
            "CH_CLOSING_PRICE": 1009.95,
            "CH_LAST_TRADED_PRICE": 1009,
            "CH_PREVIOUS_CLS_PRICE": 999.2,
            "CH_TOT_TRADED_QTY": 28315035,
            "CH_TOT_TRADED_VAL": 28381251257,
            "CH_52WEEK_HIGH_PRICE": 1059.4,
            "CH_52WEEK_LOW_PRICE": 796,
            "CH_TOTAL_TRADES": 342997,
            "CH_ISIN": "INE090A01021",
            "CH_TIMESTAMP": "2024-01-25",
            "TIMESTAMP": "2024-01-24T18:30:00.000Z",
            "createdAt": "2024-01-25T12:00:31.402Z",
            "updatedAt": "2024-01-25T12:00:31.402Z",
            "__v": 0,
            "COP_DELIV_QTY": 14229052,
            "COP_DELIV_PERC": 50.25,
            "VWAP": 1002.34,
            "mTIMESTAMP": "25-Jan-2024"
        },
        {
            "_id": "65b7937e828d6b352002b5f7",
            "CH_SYMBOL": "ICICIBANK",
            "CH_SERIES": "EQ",
            "CH_MARKET_TYPE": "N",
            "CH_TRADE_HIGH_PRICE": 1032,
            "CH_TRADE_LOW_PRICE": 1010,
            "CH_OPENING_PRICE": 1020,
            "CH_CLOSING_PRICE": 1016.4,
            "CH_LAST_TRADED_PRICE": 1018.15,
            "CH_PREVIOUS_CLS_PRICE": 1009.95,
            "CH_TOT_TRADED_QTY": 14078922,
            "CH_TOT_TRADED_VAL": 14371068911.45,
            "CH_52WEEK_HIGH_PRICE": 1059.4,
            "CH_52WEEK_LOW_PRICE": 796,
            "CH_TOTAL_TRADES": 288152,
            "CH_ISIN": "INE090A01021",
            "CH_TIMESTAMP": "2024-01-29",
            "TIMESTAMP": "2024-01-28T18:30:00.000Z",
            "createdAt": "2024-01-29T12:01:02.677Z",
            "updatedAt": "2024-01-29T12:01:02.677Z",
            "__v": 0,
            "COP_DELIV_QTY": 8312982,
            "COP_DELIV_PERC": 59.05,
            "VWAP": 1020.75,
            "mTIMESTAMP": "29-Jan-2024"
        },
        {
            "_id": "65b8e4dd828d6b35201114ba",
            "CH_SYMBOL": "ICICIBANK",
            "CH_SERIES": "EQ",
            "CH_MARKET_TYPE": "N",
            "CH_TRADE_HIGH_PRICE": 1023.85,
            "CH_TRADE_LOW_PRICE": 1008,
            "CH_OPENING_PRICE": 1014.95,
            "CH_CLOSING_PRICE": 1016.9,
            "CH_LAST_TRADED_PRICE": 1014.9,
            "CH_PREVIOUS_CLS_PRICE": 1016.4,
            "CH_TOT_TRADED_QTY": 16085742,
            "CH_TOT_TRADED_VAL": 16329641195.2,
            "CH_52WEEK_HIGH_PRICE": 1059.4,
            "CH_52WEEK_LOW_PRICE": 796,
            "CH_TOTAL_TRADES": 272053,
            "CH_ISIN": "INE090A01021",
            "CH_TIMESTAMP": "2024-01-30",
            "TIMESTAMP": "2024-01-29T18:30:00.000Z",
            "createdAt": "2024-01-30T12:00:29.033Z",
            "updatedAt": "2024-01-30T12:00:29.033Z",
            "__v": 0,
            "COP_DELIV_QTY": 8212652,
            "COP_DELIV_PERC": 51.06,
            "VWAP": 1015.16,
            "mTIMESTAMP": "30-Jan-2024"
        },
        {
            "_id": "65ba3664ae08d26e80aa86a3",
            "CH_SYMBOL": "ICICIBANK",
            "CH_SERIES": "EQ",
            "CH_MARKET_TYPE": "N",
            "CH_TRADE_HIGH_PRICE": 1039,
            "CH_TRADE_LOW_PRICE": 1003.25,
            "CH_OPENING_PRICE": 1016.8,
            "CH_CLOSING_PRICE": 1028.15,
            "CH_LAST_TRADED_PRICE": 1024.7,
            "CH_PREVIOUS_CLS_PRICE": 1016.9,
            "CH_TOT_TRADED_QTY": 25627447,
            "CH_TOT_TRADED_VAL": 26325196239.65,
            "CH_52WEEK_HIGH_PRICE": 1059.4,
            "CH_52WEEK_LOW_PRICE": 796,
            "CH_TOTAL_TRADES": 384552,
            "CH_ISIN": "INE090A01021",
            "CH_TIMESTAMP": "2024-01-31",
            "TIMESTAMP": "2024-01-30T18:30:00.000Z",
            "createdAt": "2024-01-31T12:00:36.620Z",
            "updatedAt": "2024-01-31T12:00:36.620Z",
            "__v": 0,
            "COP_DELIV_QTY": 12571213,
            "COP_DELIV_PERC": 49.05,
            "VWAP": 1027.23,
            "mTIMESTAMP": "31-Jan-2024"
        },
        {
            "_id": "65bb87fd4e395d0fc998c368",
            "CH_SYMBOL": "ICICIBANK",
            "CH_SERIES": "EQ",
            "CH_MARKET_TYPE": "N",
            "CH_TRADE_HIGH_PRICE": 1033.95,
            "CH_TRADE_LOW_PRICE": 1017.4,
            "CH_OPENING_PRICE": 1033.95,
            "CH_CLOSING_PRICE": 1025.15,
            "CH_LAST_TRADED_PRICE": 1024.7,
            "CH_PREVIOUS_CLS_PRICE": 1028.15,
            "CH_TOT_TRADED_QTY": 13058880,
            "CH_TOT_TRADED_VAL": 13394253293.6,
            "CH_52WEEK_HIGH_PRICE": 1059.4,
            "CH_52WEEK_LOW_PRICE": 796,
            "CH_TOTAL_TRADES": 240963,
            "CH_ISIN": "INE090A01021",
            "CH_TIMESTAMP": "2024-02-01",
            "TIMESTAMP": "2024-01-31T18:30:00.000Z",
            "createdAt": "2024-02-01T12:01:01.915Z",
            "updatedAt": "2024-02-01T12:01:01.915Z",
            "__v": 0,
            "COP_DELIV_QTY": 7066624,
            "COP_DELIV_PERC": 54.11,
            "VWAP": 1025.68,
            "mTIMESTAMP": "01-Feb-2024"
        },
        {
            "_id": "65bcd97e0f5bd530f2a1fe8f",
            "CH_SYMBOL": "ICICIBANK",
            "CH_SERIES": "EQ",
            "CH_MARKET_TYPE": "N",
            "CH_TRADE_HIGH_PRICE": 1050,
            "CH_TRADE_LOW_PRICE": 1021.65,
            "CH_OPENING_PRICE": 1037.1,
            "CH_CLOSING_PRICE": 1024,
            "CH_LAST_TRADED_PRICE": 1023.5,
            "CH_PREVIOUS_CLS_PRICE": 1025.15,
            "CH_TOT_TRADED_QTY": 14774650,
            "CH_TOT_TRADED_VAL": 15322579057,
            "CH_52WEEK_HIGH_PRICE": 1059.4,
            "CH_52WEEK_LOW_PRICE": 796,
            "CH_TOTAL_TRADES": 298259,
            "CH_ISIN": "INE090A01021",
            "CH_TIMESTAMP": "2024-02-02",
            "TIMESTAMP": "2024-02-01T18:30:00.000Z",
            "createdAt": "2024-02-02T12:01:02.316Z",
            "updatedAt": "2024-02-02T12:01:02.316Z",
            "__v": 0,
            "COP_DELIV_QTY": 5533876,
            "COP_DELIV_PERC": 37.46,
            "VWAP": 1037.09,
            "mTIMESTAMP": "02-Feb-2024"
        },
        {
            "_id": "65c0cf2aab72646911a03025",
            "CH_SYMBOL": "ICICIBANK",
            "CH_SERIES": "EQ",
            "CH_MARKET_TYPE": "N",
            "CH_TRADE_HIGH_PRICE": 1026.45,
            "CH_TRADE_LOW_PRICE": 1012.1,
            "CH_OPENING_PRICE": 1022.5,
            "CH_CLOSING_PRICE": 1023.5,
            "CH_LAST_TRADED_PRICE": 1021.5,
            "CH_PREVIOUS_CLS_PRICE": 1024,
            "CH_TOT_TRADED_QTY": 12948430,
            "CH_TOT_TRADED_VAL": 13213806903,
            "CH_52WEEK_HIGH_PRICE": 1059.4,
            "CH_52WEEK_LOW_PRICE": 810.3,
            "CH_TOTAL_TRADES": 252161,
            "CH_ISIN": "INE090A01021",
            "CH_TIMESTAMP": "2024-02-05",
            "TIMESTAMP": "2024-02-04T18:30:00.000Z",
            "createdAt": "2024-02-05T12:06:02.935Z",
            "updatedAt": "2024-02-05T12:06:02.935Z",
            "__v": 0,
            "COP_DELIV_QTY": 5063778,
            "COP_DELIV_PERC": 39.11,
            "VWAP": 1020.49,
            "mTIMESTAMP": "05-Feb-2024"
        },
        {
            "_id": "65c21f83982ac8e7199ce482",
            "CH_SYMBOL": "ICICIBANK",
            "CH_SERIES": "EQ",
            "CH_MARKET_TYPE": "N",
            "CH_TRADE_HIGH_PRICE": 1034.9,
            "CH_TRADE_LOW_PRICE": 1016.7,
            "CH_OPENING_PRICE": 1023.55,
            "CH_CLOSING_PRICE": 1026.4,
            "CH_LAST_TRADED_PRICE": 1027.75,
            "CH_PREVIOUS_CLS_PRICE": 1023.5,
            "CH_TOT_TRADED_QTY": 12886927,
            "CH_TOT_TRADED_VAL": 13235660038.15,
            "CH_52WEEK_HIGH_PRICE": 1059.4,
            "CH_52WEEK_LOW_PRICE": 810.3,
            "CH_TOTAL_TRADES": 203228,
            "CH_ISIN": "INE090A01021",
            "CH_TIMESTAMP": "2024-02-06",
            "TIMESTAMP": "2024-02-05T18:30:00.000Z",
            "createdAt": "2024-02-06T12:01:07.170Z",
            "updatedAt": "2024-02-06T12:01:07.170Z",
            "__v": 0,
            "COP_DELIV_QTY": 6089164,
            "COP_DELIV_PERC": 47.25,
            "VWAP": 1027.06,
            "mTIMESTAMP": "06-Feb-2024"
        },
        {
            "_id": "65c370dd9e2fb5b3bd870c34",
            "CH_SYMBOL": "ICICIBANK",
            "CH_SERIES": "EQ",
            "CH_MARKET_TYPE": "N",
            "CH_TRADE_HIGH_PRICE": 1031.55,
            "CH_TRADE_LOW_PRICE": 1013,
            "CH_OPENING_PRICE": 1028,
            "CH_CLOSING_PRICE": 1022.15,
            "CH_LAST_TRADED_PRICE": 1022.85,
            "CH_PREVIOUS_CLS_PRICE": 1026.4,
            "CH_TOT_TRADED_QTY": 16410895,
            "CH_TOT_TRADED_VAL": 16745900269.85,
            "CH_52WEEK_HIGH_PRICE": 1059.4,
            "CH_52WEEK_LOW_PRICE": 810.3,
            "CH_TOTAL_TRADES": 302775,
            "CH_ISIN": "INE090A01021",
            "CH_TIMESTAMP": "2024-02-07",
            "TIMESTAMP": "2024-02-06T18:30:00.000Z",
            "createdAt": "2024-02-07T12:00:29.468Z",
            "updatedAt": "2024-02-07T12:00:29.468Z",
            "__v": 0,
            "COP_DELIV_QTY": 7554837,
            "COP_DELIV_PERC": 46.04,
            "VWAP": 1020.41,
            "mTIMESTAMP": "07-Feb-2024"
        },
        {
            "_id": "65c4c25cc6253a074016679e",
            "CH_SYMBOL": "ICICIBANK",
            "CH_SERIES": "EQ",
            "CH_MARKET_TYPE": "N",
            "CH_TRADE_HIGH_PRICE": 1028.25,
            "CH_TRADE_LOW_PRICE": 985.25,
            "CH_OPENING_PRICE": 1024.1,
            "CH_CLOSING_PRICE": 989.3,
            "CH_LAST_TRADED_PRICE": 991.9,
            "CH_PREVIOUS_CLS_PRICE": 1022.15,
            "CH_TOT_TRADED_QTY": 20565502,
            "CH_TOT_TRADED_VAL": 20640320782.2,
            "CH_52WEEK_HIGH_PRICE": 1059.4,
            "CH_52WEEK_LOW_PRICE": 810.3,
            "CH_TOTAL_TRADES": 332222,
            "CH_ISIN": "INE090A01021",
            "CH_TIMESTAMP": "2024-02-08",
            "TIMESTAMP": "2024-02-07T18:30:00.000Z",
            "createdAt": "2024-02-08T12:00:28.052Z",
            "updatedAt": "2024-02-08T12:00:28.052Z",
            "__v": 0,
            "COP_DELIV_QTY": 11867524,
            "COP_DELIV_PERC": 57.71,
            "VWAP": 1003.64,
            "mTIMESTAMP": "08-Feb-2024"
        },
        {
            "_id": "65c613dd2ce7cc3ec0772d74",
            "CH_SYMBOL": "ICICIBANK",
            "CH_SERIES": "EQ",
            "CH_MARKET_TYPE": "N",
            "CH_TRADE_HIGH_PRICE": 1013.75,
            "CH_TRADE_LOW_PRICE": 985.5,
            "CH_OPENING_PRICE": 988.85,
            "CH_CLOSING_PRICE": 1010.7,
            "CH_LAST_TRADED_PRICE": 1010.95,
            "CH_PREVIOUS_CLS_PRICE": 989.3,
            "CH_TOT_TRADED_QTY": 12799837,
            "CH_TOT_TRADED_VAL": 12864802516.9,
            "CH_52WEEK_HIGH_PRICE": 1059.4,
            "CH_52WEEK_LOW_PRICE": 810.3,
            "CH_TOTAL_TRADES": 307855,
            "CH_ISIN": "INE090A01021",
            "CH_TIMESTAMP": "2024-02-09",
            "TIMESTAMP": "2024-02-08T18:30:00.000Z",
            "createdAt": "2024-02-09T12:00:29.152Z",
            "updatedAt": "2024-02-09T12:00:29.152Z",
            "__v": 0,
            "COP_DELIV_QTY": 7247647,
            "COP_DELIV_PERC": 56.62,
            "VWAP": 1005.08,
            "mTIMESTAMP": "09-Feb-2024"
        },
        {
            "_id": "65ca085d3d2c61c7ee71bea5",
            "CH_SYMBOL": "ICICIBANK",
            "CH_SERIES": "EQ",
            "CH_MARKET_TYPE": "N",
            "CH_TRADE_HIGH_PRICE": 1012.2,
            "CH_TRADE_LOW_PRICE": 985.25,
            "CH_OPENING_PRICE": 1010.4,
            "CH_CLOSING_PRICE": 996.1,
            "CH_LAST_TRADED_PRICE": 994.1,
            "CH_PREVIOUS_CLS_PRICE": 1010.7,
            "CH_TOT_TRADED_QTY": 8050066,
            "CH_TOT_TRADED_VAL": 8025492595.25,
            "CH_52WEEK_HIGH_PRICE": 1059.4,
            "CH_52WEEK_LOW_PRICE": 810.3,
            "CH_TOTAL_TRADES": 231523,
            "CH_ISIN": "INE090A01021",
            "CH_TIMESTAMP": "2024-02-12",
            "TIMESTAMP": "2024-02-11T18:30:00.000Z",
            "createdAt": "2024-02-12T12:00:29.114Z",
            "updatedAt": "2024-02-12T12:00:29.114Z",
            "__v": 0,
            "COP_DELIV_QTY": 3223949,
            "COP_DELIV_PERC": 40.05,
            "VWAP": 996.95,
            "mTIMESTAMP": "12-Feb-2024"
        },
        {
            "_id": "65cb59dbc77ecab986d054b8",
            "CH_SYMBOL": "ICICIBANK",
            "CH_SERIES": "EQ",
            "CH_MARKET_TYPE": "N",
            "CH_TRADE_HIGH_PRICE": 1027.05,
            "CH_TRADE_LOW_PRICE": 1000.3,
            "CH_OPENING_PRICE": 1006,
            "CH_CLOSING_PRICE": 1019.8,
            "CH_LAST_TRADED_PRICE": 1018.55,
            "CH_PREVIOUS_CLS_PRICE": 996.1,
            "CH_TOT_TRADED_QTY": 18706292,
            "CH_TOT_TRADED_VAL": 19005585172.8,
            "CH_52WEEK_HIGH_PRICE": 1059.4,
            "CH_52WEEK_LOW_PRICE": 810.3,
            "CH_TOTAL_TRADES": 294962,
            "CH_ISIN": "INE090A01021",
            "CH_TIMESTAMP": "2024-02-13",
            "TIMESTAMP": "2024-02-12T18:30:00.000Z",
            "createdAt": "2024-02-13T12:00:27.323Z",
            "updatedAt": "2024-02-13T12:00:27.323Z",
            "__v": 0,
            "COP_DELIV_QTY": 6389610,
            "COP_DELIV_PERC": 34.16,
            "VWAP": 1016,
            "mTIMESTAMP": "13-Feb-2024"
        },
        {
            "_id": "65ccab7eb3b7cee94bb06089",
            "CH_SYMBOL": "ICICIBANK",
            "CH_SERIES": "EQ",
            "CH_MARKET_TYPE": "N",
            "CH_TRADE_HIGH_PRICE": 1035.7,
            "CH_TRADE_LOW_PRICE": 1007.55,
            "CH_OPENING_PRICE": 1009.55,
            "CH_CLOSING_PRICE": 1022.7,
            "CH_LAST_TRADED_PRICE": 1020.5,
            "CH_PREVIOUS_CLS_PRICE": 1019.8,
            "CH_TOT_TRADED_QTY": 17878720,
            "CH_TOT_TRADED_VAL": 18295210771.65,
            "CH_52WEEK_HIGH_PRICE": 1059.4,
            "CH_52WEEK_LOW_PRICE": 810.3,
            "CH_TOTAL_TRADES": 333327,
            "CH_ISIN": "INE090A01021",
            "CH_TIMESTAMP": "2024-02-14",
            "TIMESTAMP": "2024-02-13T18:30:00.000Z",
            "createdAt": "2024-02-14T12:01:02.216Z",
            "updatedAt": "2024-02-14T12:01:02.216Z",
            "__v": 0,
            "COP_DELIV_QTY": 6229040,
            "COP_DELIV_PERC": 34.84,
            "VWAP": 1023.3,
            "mTIMESTAMP": "14-Feb-2024"
        },
        {
            "_id": "65cdfcfe0b93c6793ba3e4ec",
            "CH_SYMBOL": "ICICIBANK",
            "CH_SERIES": "EQ",
            "CH_MARKET_TYPE": "N",
            "CH_TRADE_HIGH_PRICE": 1026.65,
            "CH_TRADE_LOW_PRICE": 1006.6,
            "CH_OPENING_PRICE": 1022.85,
            "CH_CLOSING_PRICE": 1016.65,
            "CH_LAST_TRADED_PRICE": 1019.1,
            "CH_PREVIOUS_CLS_PRICE": 1022.7,
            "CH_TOT_TRADED_QTY": 10069878,
            "CH_TOT_TRADED_VAL": 10209072761.8,
            "CH_52WEEK_HIGH_PRICE": 1059.4,
            "CH_52WEEK_LOW_PRICE": 810.3,
            "CH_TOTAL_TRADES": 238688,
            "CH_ISIN": "INE090A01021",
            "CH_TIMESTAMP": "2024-02-15",
            "TIMESTAMP": "2024-02-14T18:30:00.000Z",
            "createdAt": "2024-02-15T12:01:02.599Z",
            "updatedAt": "2024-02-15T12:01:02.599Z",
            "__v": 0,
            "COP_DELIV_QTY": 4072687,
            "COP_DELIV_PERC": 40.44,
            "VWAP": 1013.82,
            "mTIMESTAMP": "15-Feb-2024"
        },
        {
            "_id": "65cf4e7d61aab0774d35ac12",
            "CH_SYMBOL": "ICICIBANK",
            "CH_SERIES": "EQ",
            "CH_MARKET_TYPE": "N",
            "CH_TRADE_HIGH_PRICE": 1026.2,
            "CH_TRADE_LOW_PRICE": 1016.9,
            "CH_OPENING_PRICE": 1023.2,
            "CH_CLOSING_PRICE": 1023.25,
            "CH_LAST_TRADED_PRICE": 1022.95,
            "CH_PREVIOUS_CLS_PRICE": 1016.65,
            "CH_TOT_TRADED_QTY": 7159395,
            "CH_TOT_TRADED_VAL": 7317724030.4,
            "CH_52WEEK_HIGH_PRICE": 1059.4,
            "CH_52WEEK_LOW_PRICE": 810.3,
            "CH_TOTAL_TRADES": 228404,
            "CH_ISIN": "INE090A01021",
            "CH_TIMESTAMP": "2024-02-16",
            "TIMESTAMP": "2024-02-15T18:30:00.000Z",
            "createdAt": "2024-02-16T12:01:01.981Z",
            "updatedAt": "2024-02-16T12:01:01.981Z",
            "__v": 0,
            "COP_DELIV_QTY": 3842449,
            "COP_DELIV_PERC": 53.67,
            "VWAP": 1022.11,
            "mTIMESTAMP": "16-Feb-2024"
        },
        {
            "_id": "65d39092c64559bd8f40fc47",
            "CH_SYMBOL": "ICICIBANK",
            "CH_SERIES": "EQ",
            "CH_MARKET_TYPE": "N",
            "CH_TRADE_HIGH_PRICE": 1046,
            "CH_TRADE_LOW_PRICE": 1023.35,
            "CH_OPENING_PRICE": 1023.35,
            "CH_CLOSING_PRICE": 1043.75,
            "CH_LAST_TRADED_PRICE": 1041.05,
            "CH_PREVIOUS_CLS_PRICE": 1023.25,
            "CH_TOT_TRADED_QTY": 9388255,
            "CH_TOT_TRADED_VAL": 9754860639.6,
            "CH_52WEEK_HIGH_PRICE": 1059.4,
            "CH_52WEEK_LOW_PRICE": 810.3,
            "CH_TOTAL_TRADES": 223270,
            "CH_ISIN": "INE090A01021",
            "CH_TIMESTAMP": "2024-02-19",
            "TIMESTAMP": "2024-02-18T18:30:00.000Z",
            "createdAt": "2024-02-19T17:32:02.479Z",
            "updatedAt": "2024-02-19T17:32:02.479Z",
            "__v": 0,
            "COP_DELIV_QTY": 5147259,
            "COP_DELIV_PERC": 54.83,
            "VWAP": 1039.05,
            "mTIMESTAMP": "19-Feb-2024"
        },
        {
            "_id": "65d4945d64fbe6f723b14854",
            "CH_SYMBOL": "ICICIBANK",
            "CH_SERIES": "EQ",
            "CH_MARKET_TYPE": "N",
            "CH_TRADE_HIGH_PRICE": 1052.65,
            "CH_TRADE_LOW_PRICE": 1033.25,
            "CH_OPENING_PRICE": 1041.05,
            "CH_CLOSING_PRICE": 1048.75,
            "CH_LAST_TRADED_PRICE": 1049.75,
            "CH_PREVIOUS_CLS_PRICE": 1043.75,
            "CH_TOT_TRADED_QTY": 11293528,
            "CH_TOT_TRADED_VAL": 11819391718.9,
            "CH_52WEEK_HIGH_PRICE": 1059.4,
            "CH_52WEEK_LOW_PRICE": 810.3,
            "CH_TOTAL_TRADES": 251413,
            "CH_ISIN": "INE090A01021",
            "CH_TIMESTAMP": "2024-02-20",
            "TIMESTAMP": "2024-02-19T18:30:00.000Z",
            "createdAt": "2024-02-20T12:00:29.064Z",
            "updatedAt": "2024-02-20T12:00:29.064Z",
            "__v": 0,
            "COP_DELIV_QTY": 4991710,
            "COP_DELIV_PERC": 44.2,
            "VWAP": 1046.56,
            "mTIMESTAMP": "20-Feb-2024"
        },
        {
            "_id": "65d5e5fef1fbe8e7f6d9ca31",
            "CH_SYMBOL": "ICICIBANK",
            "CH_SERIES": "EQ",
            "CH_MARKET_TYPE": "N",
            "CH_TRADE_HIGH_PRICE": 1064,
            "CH_TRADE_LOW_PRICE": 1048,
            "CH_OPENING_PRICE": 1056.8,
            "CH_CLOSING_PRICE": 1051.95,
            "CH_LAST_TRADED_PRICE": 1049.35,
            "CH_PREVIOUS_CLS_PRICE": 1048.75,
            "CH_TOT_TRADED_QTY": 15946325,
            "CH_TOT_TRADED_VAL": 16839758063.3,
            "CH_52WEEK_HIGH_PRICE": 1064,
            "CH_52WEEK_LOW_PRICE": 810.3,
            "CH_TOTAL_TRADES": 285074,
            "CH_ISIN": "INE090A01021",
            "CH_TIMESTAMP": "2024-02-21",
            "TIMESTAMP": "2024-02-20T18:30:00.000Z",
            "createdAt": "2024-02-21T12:01:02.635Z",
            "updatedAt": "2024-02-21T12:01:02.635Z",
            "__v": 0,
            "COP_DELIV_QTY": 8400930,
            "COP_DELIV_PERC": 52.68,
            "VWAP": 1056.03,
            "mTIMESTAMP": "21-Feb-2024"
        },
        {
            "_id": "65d7377e42995682861e41b7",
            "CH_SYMBOL": "ICICIBANK",
            "CH_SERIES": "EQ",
            "CH_MARKET_TYPE": "N",
            "CH_TRADE_HIGH_PRICE": 1066,
            "CH_TRADE_LOW_PRICE": 1040.3,
            "CH_OPENING_PRICE": 1056,
            "CH_CLOSING_PRICE": 1062.7,
            "CH_LAST_TRADED_PRICE": 1061.55,
            "CH_PREVIOUS_CLS_PRICE": 1051.95,
            "CH_TOT_TRADED_QTY": 13432573,
            "CH_TOT_TRADED_VAL": 14165481752.55,
            "CH_52WEEK_HIGH_PRICE": 1066,
            "CH_52WEEK_LOW_PRICE": 810.3,
            "CH_TOTAL_TRADES": 289172,
            "CH_ISIN": "INE090A01021",
            "CH_TIMESTAMP": "2024-02-22",
            "TIMESTAMP": "2024-02-21T18:30:00.000Z",
            "createdAt": "2024-02-22T12:01:02.567Z",
            "updatedAt": "2024-02-22T12:01:02.567Z",
            "__v": 0,
            "COP_DELIV_QTY": 4966739,
            "COP_DELIV_PERC": 36.98,
            "VWAP": 1054.56,
            "mTIMESTAMP": "22-Feb-2024"
        },
        {
            "_id": "671bdd8e3d0207f9766f7271",
            "CH_SYMBOL": "ICICIBANK",
            "CH_SERIES": "EQ",
            "CH_MARKET_TYPE": "N",
            "CH_TIMESTAMP": "2024-02-23",
            "TIMESTAMP": "2024-02-22T18:30:00.000Z",
            "CH_TRADE_HIGH_PRICE": 1070,
            "CH_TRADE_LOW_PRICE": 1057.65,
            "CH_OPENING_PRICE": 1070,
            "CH_CLOSING_PRICE": 1061.3,
            "CH_LAST_TRADED_PRICE": 1061.25,
            "CH_PREVIOUS_CLS_PRICE": 1062.7,
            "CH_TOT_TRADED_QTY": 13142759,
            "CH_TOT_TRADED_VAL": 13982766720.4,
            "CH_52WEEK_HIGH_PRICE": 1070,
            "CH_52WEEK_LOW_PRICE": 810.3,
            "CH_TOTAL_TRADES": 217544,
            "CH_ISIN": "INE090A01021",
            "createdAt": "2024-10-25T18:03:58.131Z",
            "updatedAt": "2024-10-25T18:03:58.131Z",
            "__v": 0,
            "COP_DELIV_QTY": 8343213,
            "COP_DELIV_PERC": 63.48,
            "VWAP": 1063.91,
            "mTIMESTAMP": "23-Feb-2024"
        },
        {
            "_id": "65dc7d5b18353a15cfb09a64",
            "CH_SYMBOL": "ICICIBANK",
            "CH_SERIES": "EQ",
            "CH_MARKET_TYPE": "N",
            "CH_TIMESTAMP": "2024-02-26",
            "TIMESTAMP": "2024-02-25T18:30:00.000Z",
            "CH_TRADE_HIGH_PRICE": 1062.3,
            "CH_TRADE_LOW_PRICE": 1050.5,
            "CH_OPENING_PRICE": 1053.1,
            "CH_CLOSING_PRICE": 1054.2,
            "CH_LAST_TRADED_PRICE": 1053.75,
            "CH_PREVIOUS_CLS_PRICE": 1061.3,
            "CH_TOT_TRADED_QTY": 7875941,
            "CH_TOT_TRADED_VAL": 8313978243.65,
            "CH_52WEEK_HIGH_PRICE": 1070,
            "CH_52WEEK_LOW_PRICE": 810.3,
            "CH_TOTAL_TRADES": 187011,
            "CH_ISIN": "INE090A01021",
            "createdAt": "2024-02-26T12:00:27.377Z",
            "updatedAt": "2024-02-26T12:00:27.377Z",
            "__v": 0,
            "COP_DELIV_QTY": 5027751,
            "COP_DELIV_PERC": 63.84,
            "VWAP": 1055.62,
            "mTIMESTAMP": "26-Feb-2024"
        },
        {
            "_id": "65ddcedddc3d5b40c3c1e827",
            "CH_SYMBOL": "ICICIBANK",
            "CH_SERIES": "EQ",
            "CH_MARKET_TYPE": "N",
            "CH_TIMESTAMP": "2024-02-27",
            "TIMESTAMP": "2024-02-26T18:30:00.000Z",
            "CH_TRADE_HIGH_PRICE": 1066.2,
            "CH_TRADE_LOW_PRICE": 1046.5,
            "CH_OPENING_PRICE": 1050.75,
            "CH_CLOSING_PRICE": 1060.2,
            "CH_LAST_TRADED_PRICE": 1061.5,
            "CH_PREVIOUS_CLS_PRICE": 1054.2,
            "CH_TOT_TRADED_QTY": 10580973,
            "CH_TOT_TRADED_VAL": 11185895021.2,
            "CH_52WEEK_HIGH_PRICE": 1070,
            "CH_52WEEK_LOW_PRICE": 810.3,
            "CH_TOTAL_TRADES": 203486,
            "CH_ISIN": "INE090A01021",
            "createdAt": "2024-02-27T12:00:29.038Z",
            "updatedAt": "2024-02-27T12:00:29.038Z",
            "__v": 0,
            "COP_DELIV_QTY": 5898487,
            "COP_DELIV_PERC": 55.75,
            "VWAP": 1057.17,
            "mTIMESTAMP": "27-Feb-2024"
        },
        {
            "_id": "65df207e3ab4615b76386c6f",
            "CH_SYMBOL": "ICICIBANK",
            "CH_SERIES": "EQ",
            "CH_MARKET_TYPE": "N",
            "CH_TIMESTAMP": "2024-02-28",
            "TIMESTAMP": "2024-02-27T18:30:00.000Z",
            "CH_TRADE_HIGH_PRICE": 1064.85,
            "CH_TRADE_LOW_PRICE": 1042.15,
            "CH_OPENING_PRICE": 1063,
            "CH_CLOSING_PRICE": 1046.2,
            "CH_LAST_TRADED_PRICE": 1046.6,
            "CH_PREVIOUS_CLS_PRICE": 1060.2,
            "CH_TOT_TRADED_QTY": 7730332,
            "CH_TOT_TRADED_VAL": 8126074219.15,
            "CH_52WEEK_HIGH_PRICE": 1070,
            "CH_52WEEK_LOW_PRICE": 810.3,
            "CH_TOTAL_TRADES": 175450,
            "CH_ISIN": "INE090A01021",
            "createdAt": "2024-02-28T12:01:02.137Z",
            "updatedAt": "2024-02-28T12:01:02.137Z",
            "__v": 0,
            "COP_DELIV_QTY": 3965568,
            "COP_DELIV_PERC": 51.3,
            "VWAP": 1051.19,
            "mTIMESTAMP": "28-Feb-2024"
        },
        {
            "_id": "65e071fe79a06978a17fb55f",
            "CH_SYMBOL": "ICICIBANK",
            "CH_SERIES": "EQ",
            "CH_MARKET_TYPE": "N",
            "CH_TIMESTAMP": "2024-02-29",
            "TIMESTAMP": "2024-02-28T18:30:00.000Z",
            "CH_TRADE_HIGH_PRICE": 1060.7,
            "CH_TRADE_LOW_PRICE": 1038.5,
            "CH_OPENING_PRICE": 1043.05,
            "CH_CLOSING_PRICE": 1052.2,
            "CH_LAST_TRADED_PRICE": 1054.95,
            "CH_PREVIOUS_CLS_PRICE": 1046.2,
            "CH_TOT_TRADED_QTY": 20944844,
            "CH_TOT_TRADED_VAL": 22022802548.35,
            "CH_52WEEK_HIGH_PRICE": 1070,
            "CH_52WEEK_LOW_PRICE": 810.3,
            "CH_TOTAL_TRADES": 343777,
            "CH_ISIN": "INE090A01021",
            "createdAt": "2024-02-29T12:01:02.058Z",
            "updatedAt": "2024-02-29T12:01:02.058Z",
            "__v": 0,
            "COP_DELIV_QTY": 10421268,
            "COP_DELIV_PERC": 49.76,
            "VWAP": 1051.47,
            "mTIMESTAMP": "29-Feb-2024"
        },
        {
            "_id": "65e1c37ec9980b75461222da",
            "CH_SYMBOL": "ICICIBANK",
            "CH_SERIES": "EQ",
            "CH_MARKET_TYPE": "N",
            "CH_TIMESTAMP": "2024-03-01",
            "TIMESTAMP": "2024-02-29T18:30:00.000Z",
            "CH_TRADE_HIGH_PRICE": 1089.95,
            "CH_TRADE_LOW_PRICE": 1054,
            "CH_OPENING_PRICE": 1055,
            "CH_CLOSING_PRICE": 1086.9,
            "CH_LAST_TRADED_PRICE": 1085,
            "CH_PREVIOUS_CLS_PRICE": 1052.2,
            "CH_TOT_TRADED_QTY": 14909562,
            "CH_TOT_TRADED_VAL": 16093696257.8,
            "CH_52WEEK_HIGH_PRICE": 1089.95,
            "CH_52WEEK_LOW_PRICE": 810.3,
            "CH_TOTAL_TRADES": 315463,
            "CH_ISIN": "INE090A01021",
            "createdAt": "2024-03-01T12:01:02.590Z",
            "updatedAt": "2024-03-01T12:01:02.590Z",
            "__v": 0,
            "COP_DELIV_QTY": 9592724,
            "COP_DELIV_PERC": 64.34,
            "VWAP": 1079.42,
            "mTIMESTAMP": "01-Mar-2024"
        },
        {
            "_id": "65e2f19be343cf897421d5c3",
            "CH_SYMBOL": "ICICIBANK",
            "CH_SERIES": "EQ",
            "CH_MARKET_TYPE": "N",
            "CH_TIMESTAMP": "2024-03-02",
            "TIMESTAMP": "2024-03-01T18:30:00.000Z",
            "CH_TRADE_HIGH_PRICE": 1089.45,
            "CH_TRADE_LOW_PRICE": 1080.5,
            "CH_OPENING_PRICE": 1087.25,
            "CH_CLOSING_PRICE": 1084.65,
            "CH_LAST_TRADED_PRICE": 1083.9,
            "CH_PREVIOUS_CLS_PRICE": 1086.9,
            "CH_TOT_TRADED_QTY": 481475,
            "CH_TOT_TRADED_VAL": 522100593.2,
            "CH_52WEEK_HIGH_PRICE": 1089.95,
            "CH_52WEEK_LOW_PRICE": 810.3,
            "CH_TOTAL_TRADES": 14375,
            "CH_ISIN": "INE090A01021",
            "createdAt": "2024-03-02T09:30:03.906Z",
            "updatedAt": "2024-03-02T09:30:03.906Z",
            "__v": 0,
            "COP_DELIV_QTY": 180404,
            "COP_DELIV_PERC": 37.47,
            "VWAP": 1084.38,
            "mTIMESTAMP": "02-Mar-2024"
        },
        {
            "_id": "65e5b7fe3d2532dd72f73d03",
            "CH_SYMBOL": "ICICIBANK",
            "CH_SERIES": "EQ",
            "CH_MARKET_TYPE": "N",
            "CH_TIMESTAMP": "2024-03-04",
            "TIMESTAMP": "2024-03-03T18:30:00.000Z",
            "CH_TRADE_HIGH_PRICE": 1095,
            "CH_TRADE_LOW_PRICE": 1080.1,
            "CH_OPENING_PRICE": 1081,
            "CH_CLOSING_PRICE": 1092.35,
            "CH_LAST_TRADED_PRICE": 1090.9,
            "CH_PREVIOUS_CLS_PRICE": 1084.65,
            "CH_TOT_TRADED_QTY": 11424581,
            "CH_TOT_TRADED_VAL": 12453254625.85,
            "CH_52WEEK_HIGH_PRICE": 1095,
            "CH_52WEEK_LOW_PRICE": 810.3,
            "CH_TOTAL_TRADES": 251185,
            "CH_ISIN": "INE090A01021",
            "createdAt": "2024-03-04T12:01:02.378Z",
            "updatedAt": "2024-03-04T12:01:02.378Z",
            "__v": 0,
            "COP_DELIV_QTY": 7785048,
            "COP_DELIV_PERC": 68.14,
            "VWAP": 1090.04,
            "mTIMESTAMP": "04-Mar-2024"
        },
        {
            "_id": "65e7097e5dbf82f0d7056e44",
            "CH_SYMBOL": "ICICIBANK",
            "CH_SERIES": "EQ",
            "CH_MARKET_TYPE": "N",
            "CH_TIMESTAMP": "2024-03-05",
            "TIMESTAMP": "2024-03-04T18:30:00.000Z",
            "CH_TRADE_HIGH_PRICE": 1099.5,
            "CH_TRADE_LOW_PRICE": 1076.5,
            "CH_OPENING_PRICE": 1086.2,
            "CH_CLOSING_PRICE": 1088.05,
            "CH_LAST_TRADED_PRICE": 1087.85,
            "CH_PREVIOUS_CLS_PRICE": 1092.35,
            "CH_TOT_TRADED_QTY": 9222544,
            "CH_TOT_TRADED_VAL": 10048890642.95,
            "CH_52WEEK_HIGH_PRICE": 1099.5,
            "CH_52WEEK_LOW_PRICE": 810.3,
            "CH_TOTAL_TRADES": 258890,
            "CH_ISIN": "INE090A01021",
            "createdAt": "2024-03-05T12:01:02.240Z",
            "updatedAt": "2024-03-05T12:01:02.240Z",
            "__v": 0,
            "COP_DELIV_QTY": 4745297,
            "COP_DELIV_PERC": 51.45,
            "VWAP": 1089.6,
            "mTIMESTAMP": "05-Mar-2024"
        },
        {
            "_id": "65e85adfd8972ba31a12de80",
            "CH_SYMBOL": "ICICIBANK",
            "CH_SERIES": "EQ",
            "CH_MARKET_TYPE": "N",
            "CH_TIMESTAMP": "2024-03-06",
            "TIMESTAMP": "2024-03-05T18:30:00.000Z",
            "CH_TRADE_HIGH_PRICE": 1113.55,
            "CH_TRADE_LOW_PRICE": 1080.3,
            "CH_OPENING_PRICE": 1080.3,
            "CH_CLOSING_PRICE": 1097.1,
            "CH_LAST_TRADED_PRICE": 1099,
            "CH_PREVIOUS_CLS_PRICE": 1088.05,
            "CH_TOT_TRADED_QTY": 21796484,
            "CH_TOT_TRADED_VAL": 24011191501.45,
            "CH_52WEEK_HIGH_PRICE": 1113.55,
            "CH_52WEEK_LOW_PRICE": 810.3,
            "CH_TOTAL_TRADES": 364582,
            "CH_ISIN": "INE090A01021",
            "createdAt": "2024-03-06T12:00:31.577Z",
            "updatedAt": "2024-03-06T12:00:31.577Z",
            "__v": 0,
            "COP_DELIV_QTY": 10180700,
            "COP_DELIV_PERC": 46.71,
            "VWAP": 1101.61,
            "mTIMESTAMP": "06-Mar-2024"
        },
        {
            "_id": "65e9ac7d3d2532dd72f7b0de",
            "CH_SYMBOL": "ICICIBANK",
            "CH_SERIES": "EQ",
            "CH_MARKET_TYPE": "N",
            "CH_TIMESTAMP": "2024-03-07",
            "TIMESTAMP": "2024-03-06T18:30:00.000Z",
            "CH_TRADE_HIGH_PRICE": 1095,
            "CH_TRADE_LOW_PRICE": 1082.7,
            "CH_OPENING_PRICE": 1094.95,
            "CH_CLOSING_PRICE": 1087.95,
            "CH_LAST_TRADED_PRICE": 1086.5,
            "CH_PREVIOUS_CLS_PRICE": 1097.1,
            "CH_TOT_TRADED_QTY": 9963926,
            "CH_TOT_TRADED_VAL": 10843732033.05,
            "CH_52WEEK_HIGH_PRICE": 1113.55,
            "CH_52WEEK_LOW_PRICE": 810.3,
            "CH_TOTAL_TRADES": 262108,
            "CH_ISIN": "INE090A01021",
            "createdAt": "2024-03-07T12:01:01.913Z",
            "updatedAt": "2024-03-07T12:01:01.913Z",
            "__v": 0,
            "COP_DELIV_QTY": 5743168,
            "COP_DELIV_PERC": 57.64,
            "VWAP": 1088.3,
            "mTIMESTAMP": "07-Mar-2024"
        },
        {
            "_id": "65ef05b5646a0fb86a14269c",
            "CH_SYMBOL": "ICICIBANK",
            "CH_SERIES": "EQ",
            "CH_MARKET_TYPE": "N",
            "CH_TIMESTAMP": "2024-03-11",
            "TIMESTAMP": "2024-03-10T18:30:00.000Z",
            "CH_TRADE_HIGH_PRICE": 1087.95,
            "CH_TRADE_LOW_PRICE": 1076.75,
            "CH_OPENING_PRICE": 1087.95,
            "CH_CLOSING_PRICE": 1078.7,
            "CH_LAST_TRADED_PRICE": 1077.5,
            "CH_PREVIOUS_CLS_PRICE": 1087.95,
            "CH_TOT_TRADED_QTY": 13310362,
            "CH_TOT_TRADED_VAL": 14389279964.5,
            "CH_52WEEK_HIGH_PRICE": 1113.55,
            "CH_52WEEK_LOW_PRICE": 810.3,
            "CH_TOTAL_TRADES": 250456,
            "CH_ISIN": "INE090A01021",
            "createdAt": "2024-03-11T13:23:02.006Z",
            "updatedAt": "2024-03-11T13:23:02.006Z",
            "__v": 0,
            "COP_DELIV_QTY": 9577327,
            "COP_DELIV_PERC": 71.95,
            "VWAP": 1081.06,
            "mTIMESTAMP": "11-Mar-2024"
        },
        {
            "_id": "65f043dd249c86c7a88f9c5d",
            "CH_SYMBOL": "ICICIBANK",
            "CH_SERIES": "EQ",
            "CH_MARKET_TYPE": "N",
            "CH_TIMESTAMP": "2024-03-12",
            "TIMESTAMP": "2024-03-11T18:30:00.000Z",
            "CH_TRADE_HIGH_PRICE": 1094.8,
            "CH_TRADE_LOW_PRICE": 1055.65,
            "CH_OPENING_PRICE": 1077.05,
            "CH_CLOSING_PRICE": 1076.85,
            "CH_LAST_TRADED_PRICE": 1075.05,
            "CH_PREVIOUS_CLS_PRICE": 1078.7,
            "CH_TOT_TRADED_QTY": 21785435,
            "CH_TOT_TRADED_VAL": 23482625405.85,
            "CH_52WEEK_HIGH_PRICE": 1113.55,
            "CH_52WEEK_LOW_PRICE": 810.3,
            "CH_TOTAL_TRADES": 304992,
            "CH_ISIN": "INE090A01021",
            "createdAt": "2024-03-12T12:00:29.467Z",
            "updatedAt": "2024-03-12T12:00:29.467Z",
            "__v": 0,
            "COP_DELIV_QTY": 10142990,
            "COP_DELIV_PERC": 46.56,
            "VWAP": 1077.9,
            "mTIMESTAMP": "12-Mar-2024"
        },
        {
            "_id": "65f19561e2a16978fb6c9cb4",
            "CH_SYMBOL": "ICICIBANK",
            "CH_SERIES": "EQ",
            "CH_MARKET_TYPE": "N",
            "CH_TIMESTAMP": "2024-03-13",
            "TIMESTAMP": "2024-03-12T18:30:00.000Z",
            "CH_TRADE_HIGH_PRICE": 1089.65,
            "CH_TRADE_LOW_PRICE": 1073.15,
            "CH_OPENING_PRICE": 1077.15,
            "CH_CLOSING_PRICE": 1083.95,
            "CH_LAST_TRADED_PRICE": 1082,
            "CH_PREVIOUS_CLS_PRICE": 1076.85,
            "CH_TOT_TRADED_QTY": 24855870,
            "CH_TOT_TRADED_VAL": 26953204669.15,
            "CH_52WEEK_HIGH_PRICE": 1113.55,
            "CH_52WEEK_LOW_PRICE": 810.3,
            "CH_TOTAL_TRADES": 361717,
            "CH_ISIN": "INE090A01021",
            "createdAt": "2024-03-13T12:00:33.359Z",
            "updatedAt": "2024-03-13T12:00:33.359Z",
            "__v": 0,
            "COP_DELIV_QTY": 13165624,
            "COP_DELIV_PERC": 52.97,
            "VWAP": 1084.38,
            "mTIMESTAMP": "13-Mar-2024"
        },
        {
            "_id": "65f2e6feba531f76a2e970b0",
            "CH_SYMBOL": "ICICIBANK",
            "CH_SERIES": "EQ",
            "CH_MARKET_TYPE": "N",
            "CH_TIMESTAMP": "2024-03-14",
            "TIMESTAMP": "2024-03-13T18:30:00.000Z",
            "CH_TRADE_HIGH_PRICE": 1097.1,
            "CH_TRADE_LOW_PRICE": 1075.05,
            "CH_OPENING_PRICE": 1080,
            "CH_CLOSING_PRICE": 1083.6,
            "CH_LAST_TRADED_PRICE": 1084.35,
            "CH_PREVIOUS_CLS_PRICE": 1083.95,
            "CH_TOT_TRADED_QTY": 14231421,
            "CH_TOT_TRADED_VAL": 15455740913.55,
            "CH_52WEEK_HIGH_PRICE": 1113.55,
            "CH_52WEEK_LOW_PRICE": 810.3,
            "CH_TOTAL_TRADES": 259807,
            "CH_ISIN": "INE090A01021",
            "createdAt": "2024-03-14T12:01:02.110Z",
            "updatedAt": "2024-03-14T12:01:02.110Z",
            "__v": 0,
            "COP_DELIV_QTY": 6207330,
            "COP_DELIV_PERC": 43.62,
            "VWAP": 1086.03,
            "mTIMESTAMP": "14-Mar-2024"
        },
        {
            "_id": "65f4387e449d8ee9fc012785",
            "CH_SYMBOL": "ICICIBANK",
            "CH_SERIES": "EQ",
            "CH_MARKET_TYPE": "N",
            "CH_TIMESTAMP": "2024-03-15",
            "TIMESTAMP": "2024-03-14T18:30:00.000Z",
            "CH_TRADE_HIGH_PRICE": 1086.25,
            "CH_TRADE_LOW_PRICE": 1070,
            "CH_OPENING_PRICE": 1072,
            "CH_CLOSING_PRICE": 1080.35,
            "CH_LAST_TRADED_PRICE": 1073.9,
            "CH_PREVIOUS_CLS_PRICE": 1083.6,
            "CH_TOT_TRADED_QTY": 66192734,
            "CH_TOT_TRADED_VAL": 71499718294.1,
            "CH_52WEEK_HIGH_PRICE": 1113.55,
            "CH_52WEEK_LOW_PRICE": 810.3,
            "CH_TOTAL_TRADES": 347312,
            "CH_ISIN": "INE090A01021",
            "createdAt": "2024-03-15T12:01:02.841Z",
            "updatedAt": "2024-03-15T12:01:02.841Z",
            "__v": 0,
            "COP_DELIV_QTY": 49077479,
            "COP_DELIV_PERC": 74.14,
            "VWAP": 1080.17,
            "mTIMESTAMP": "15-Mar-2024"
        },
        {
            "_id": "65f82cdc232b4b49d101fc17",
            "CH_SYMBOL": "ICICIBANK",
            "CH_SERIES": "EQ",
            "CH_MARKET_TYPE": "N",
            "CH_TIMESTAMP": "2024-03-18",
            "TIMESTAMP": "2024-03-17T18:30:00.000Z",
            "CH_TRADE_HIGH_PRICE": 1084.8,
            "CH_TRADE_LOW_PRICE": 1060.05,
            "CH_OPENING_PRICE": 1075.05,
            "CH_CLOSING_PRICE": 1081.2,
            "CH_LAST_TRADED_PRICE": 1082.1,
            "CH_PREVIOUS_CLS_PRICE": 1080.35,
            "CH_TOT_TRADED_QTY": 8769440,
            "CH_TOT_TRADED_VAL": 9441285942.75,
            "CH_52WEEK_HIGH_PRICE": 1113.55,
            "CH_52WEEK_LOW_PRICE": 825,
            "CH_TOTAL_TRADES": 253537,
            "CH_ISIN": "INE090A01021",
            "createdAt": "2024-03-18T12:00:28.898Z",
            "updatedAt": "2024-03-18T12:00:28.898Z",
            "__v": 0,
            "COP_DELIV_QTY": 4101264,
            "COP_DELIV_PERC": 46.77,
            "VWAP": 1076.61,
            "mTIMESTAMP": "18-Mar-2024"
        },
        {
            "_id": "65f97e7e498fc9e86760f83b",
            "CH_SYMBOL": "ICICIBANK",
            "CH_SERIES": "EQ",
            "CH_MARKET_TYPE": "N",
            "CH_TIMESTAMP": "2024-03-19",
            "TIMESTAMP": "2024-03-18T18:30:00.000Z",
            "CH_TRADE_HIGH_PRICE": 1088.75,
            "CH_TRADE_LOW_PRICE": 1075.25,
            "CH_OPENING_PRICE": 1078.45,
            "CH_CLOSING_PRICE": 1083.95,
            "CH_LAST_TRADED_PRICE": 1081.45,
            "CH_PREVIOUS_CLS_PRICE": 1081.2,
            "CH_TOT_TRADED_QTY": 16708715,
            "CH_TOT_TRADED_VAL": 18088899237.65,
            "CH_52WEEK_HIGH_PRICE": 1113.55,
            "CH_52WEEK_LOW_PRICE": 825,
            "CH_TOTAL_TRADES": 367746,
            "CH_ISIN": "INE090A01021",
            "createdAt": "2024-03-19T12:01:02.689Z",
            "updatedAt": "2024-03-19T12:01:02.689Z",
            "__v": 0,
            "COP_DELIV_QTY": 10342948,
            "COP_DELIV_PERC": 61.9,
            "VWAP": 1082.6,
            "mTIMESTAMP": "19-Mar-2024"
        },
        {
            "_id": "65facfdd875450dd91210a07",
            "CH_SYMBOL": "ICICIBANK",
            "CH_SERIES": "EQ",
            "CH_MARKET_TYPE": "N",
            "CH_TIMESTAMP": "2024-03-20",
            "TIMESTAMP": "2024-03-19T18:30:00.000Z",
            "CH_TRADE_HIGH_PRICE": 1090,
            "CH_TRADE_LOW_PRICE": 1067.5,
            "CH_OPENING_PRICE": 1080,
            "CH_CLOSING_PRICE": 1084.5,
            "CH_LAST_TRADED_PRICE": 1087,
            "CH_PREVIOUS_CLS_PRICE": 1083.95,
            "CH_TOT_TRADED_QTY": 18725251,
            "CH_TOT_TRADED_VAL": 20246525010.95,
            "CH_52WEEK_HIGH_PRICE": 1113.55,
            "CH_52WEEK_LOW_PRICE": 825,
            "CH_TOTAL_TRADES": 365151,
            "CH_ISIN": "INE090A01021",
            "createdAt": "2024-03-20T12:00:29.560Z",
            "updatedAt": "2024-03-20T12:00:29.560Z",
            "__v": 0,
            "COP_DELIV_QTY": 8233921,
            "COP_DELIV_PERC": 43.97,
            "VWAP": 1081.24,
            "mTIMESTAMP": "20-Mar-2024"
        },
        {
            "_id": "65fc217eac280a1df6bce083",
            "CH_SYMBOL": "ICICIBANK",
            "CH_SERIES": "EQ",
            "CH_MARKET_TYPE": "N",
            "CH_TIMESTAMP": "2024-03-21",
            "TIMESTAMP": "2024-03-20T18:30:00.000Z",
            "CH_TRADE_HIGH_PRICE": 1100,
            "CH_TRADE_LOW_PRICE": 1079.15,
            "CH_OPENING_PRICE": 1092,
            "CH_CLOSING_PRICE": 1081.8,
            "CH_LAST_TRADED_PRICE": 1081.5,
            "CH_PREVIOUS_CLS_PRICE": 1084.5,
            "CH_TOT_TRADED_QTY": 19992607,
            "CH_TOT_TRADED_VAL": 21719605114.85,
            "CH_52WEEK_HIGH_PRICE": 1113.55,
            "CH_52WEEK_LOW_PRICE": 825,
            "CH_TOTAL_TRADES": 252414,
            "CH_ISIN": "INE090A01021",
            "createdAt": "2024-03-21T12:01:02.435Z",
            "updatedAt": "2024-03-21T12:01:02.435Z",
            "__v": 0,
            "COP_DELIV_QTY": 13607650,
            "COP_DELIV_PERC": 68.06,
            "VWAP": 1086.38,
            "mTIMESTAMP": "21-Mar-2024"
        },
        {
            "_id": "65fd72dbb19be7cbf8a58af5",
            "CH_SYMBOL": "ICICIBANK",
            "CH_SERIES": "EQ",
            "CH_MARKET_TYPE": "N",
            "CH_TIMESTAMP": "2024-03-22",
            "TIMESTAMP": "2024-03-21T18:30:00.000Z",
            "CH_TRADE_HIGH_PRICE": 1093.7,
            "CH_TRADE_LOW_PRICE": 1078.7,
            "CH_OPENING_PRICE": 1081.15,
            "CH_CLOSING_PRICE": 1090.3,
            "CH_LAST_TRADED_PRICE": 1089.5,
            "CH_PREVIOUS_CLS_PRICE": 1081.8,
            "CH_TOT_TRADED_QTY": 17214415,
            "CH_TOT_TRADED_VAL": 18762240505.05,
            "CH_52WEEK_HIGH_PRICE": 1113.55,
            "CH_52WEEK_LOW_PRICE": 825,
            "CH_TOTAL_TRADES": 258317,
            "CH_ISIN": "INE090A01021",
            "createdAt": "2024-03-22T12:00:27.097Z",
            "updatedAt": "2024-03-22T12:00:27.097Z",
            "__v": 0,
            "COP_DELIV_QTY": 10440853,
            "COP_DELIV_PERC": 60.65,
            "VWAP": 1089.91,
            "mTIMESTAMP": "22-Mar-2024"
        },
        {
            "_id": "6602db36f04eb262462f56d1",
            "CH_SYMBOL": "ICICIBANK",
            "CH_SERIES": "EQ",
            "CH_MARKET_TYPE": "N",
            "CH_TIMESTAMP": "2024-03-26",
            "TIMESTAMP": "2024-03-25T18:30:00.000Z",
            "CH_TRADE_HIGH_PRICE": 1089.15,
            "CH_TRADE_LOW_PRICE": 1076.95,
            "CH_OPENING_PRICE": 1081,
            "CH_CLOSING_PRICE": 1083.7,
            "CH_LAST_TRADED_PRICE": 1083.4,
            "CH_PREVIOUS_CLS_PRICE": 1090.3,
            "CH_TOT_TRADED_QTY": 13367635,
            "CH_TOT_TRADED_VAL": 14480333014.75,
            "CH_52WEEK_HIGH_PRICE": 1113.55,
            "CH_52WEEK_LOW_PRICE": 844.05,
            "CH_TOTAL_TRADES": 213520,
            "CH_ISIN": "INE090A01021",
            "createdAt": "2024-03-26T14:27:02.851Z",
            "updatedAt": "2024-03-26T14:27:02.851Z",
            "__v": 0,
            "COP_DELIV_QTY": 7584977,
            "COP_DELIV_PERC": 56.74,
            "VWAP": 1083.24,
            "mTIMESTAMP": "26-Mar-2024"
        },
        {
            "_id": "66040cccf79bf22bf30dfa26",
            "CH_SYMBOL": "ICICIBANK",
            "CH_SERIES": "EQ",
            "CH_MARKET_TYPE": "N",
            "CH_TRADE_HIGH_PRICE": 1092.5,
            "CH_TRADE_LOW_PRICE": 1079.55,
            "CH_OPENING_PRICE": 1083.7,
            "CH_CLOSING_PRICE": 1083.75,
            "CH_LAST_TRADED_PRICE": 1085,
            "CH_PREVIOUS_CLS_PRICE": 1083.7,
            "CH_TOT_TRADED_QTY": 26907245,
            "CH_TOT_TRADED_VAL": 29202142587.1,
            "CH_52WEEK_HIGH_PRICE": 1113.55,
            "CH_52WEEK_LOW_PRICE": 844.05,
            "CH_TOTAL_TRADES": 318363,
            "CH_ISIN": "INE090A01021",
            "CH_TIMESTAMP": "2024-03-27",
            "TIMESTAMP": "2024-03-26T18:30:00.000Z",
            "createdAt": "2024-03-27T12:10:52.175Z",
            "updatedAt": "2024-03-27T12:10:52.175Z",
            "__v": 0,
            "COP_DELIV_QTY": 13797010,
            "COP_DELIV_PERC": 51.28,
            "VWAP": 1085.29,
            "mTIMESTAMP": "27-Mar-2024"
        },
        {
            "_id": "66055bfe7a3e097b6f85804a",
            "CH_SYMBOL": "ICICIBANK",
            "CH_SERIES": "EQ",
            "CH_MARKET_TYPE": "N",
            "CH_TIMESTAMP": "2024-03-28",
            "TIMESTAMP": "2024-03-27T18:30:00.000Z",
            "CH_TRADE_HIGH_PRICE": 1105.05,
            "CH_TRADE_LOW_PRICE": 1085,
            "CH_OPENING_PRICE": 1085,
            "CH_CLOSING_PRICE": 1093.3,
            "CH_LAST_TRADED_PRICE": 1096.05,
            "CH_PREVIOUS_CLS_PRICE": 1083.75,
            "CH_TOT_TRADED_QTY": 22070566,
            "CH_TOT_TRADED_VAL": 24234485223.65,
            "CH_52WEEK_HIGH_PRICE": 1113.55,
            "CH_52WEEK_LOW_PRICE": 844.05,
            "CH_TOTAL_TRADES": 369595,
            "CH_ISIN": "INE090A01021",
            "createdAt": "2024-03-28T12:01:02.598Z",
            "updatedAt": "2024-03-28T12:01:02.598Z",
            "__v": 0,
            "COP_DELIV_QTY": 11950777,
            "COP_DELIV_PERC": 54.15,
            "VWAP": 1098.05,
            "mTIMESTAMP": "28-Mar-2024"
        },
        {
            "_id": "660aa1feb6a351c2ba40cb97",
            "CH_SYMBOL": "ICICIBANK",
            "CH_SERIES": "EQ",
            "CH_MARKET_TYPE": "N",
            "CH_TIMESTAMP": "2024-04-01",
            "TIMESTAMP": "2024-03-31T18:30:00.000Z",
            "CH_TRADE_HIGH_PRICE": 1102.95,
            "CH_TRADE_LOW_PRICE": 1094.45,
            "CH_OPENING_PRICE": 1096.05,
            "CH_CLOSING_PRICE": 1099.65,
            "CH_LAST_TRADED_PRICE": 1098.7,
            "CH_PREVIOUS_CLS_PRICE": 1093.3,
            "CH_TOT_TRADED_QTY": 10848191,
            "CH_TOT_TRADED_VAL": 11916581584.35,
            "CH_52WEEK_HIGH_PRICE": 1113.55,
            "CH_52WEEK_LOW_PRICE": 864.4,
            "CH_TOTAL_TRADES": 191651,
            "CH_ISIN": "INE090A01021",
            "createdAt": "2024-04-01T12:01:02.297Z",
            "updatedAt": "2024-04-01T12:01:02.297Z",
            "__v": 0,
            "COP_DELIV_QTY": 7348389,
            "COP_DELIV_PERC": 67.74,
            "VWAP": 1098.49,
            "mTIMESTAMP": "01-Apr-2024"
        },
        {
            "_id": "660bf35b4a76eba9c31e0f7c",
            "CH_SYMBOL": "ICICIBANK",
            "CH_SERIES": "EQ",
            "CH_MARKET_TYPE": "N",
            "CH_TIMESTAMP": "2024-04-02",
            "TIMESTAMP": "2024-04-01T18:30:00.000Z",
            "CH_TRADE_HIGH_PRICE": 1094.45,
            "CH_TRADE_LOW_PRICE": 1079.25,
            "CH_OPENING_PRICE": 1094.45,
            "CH_CLOSING_PRICE": 1081.2,
            "CH_LAST_TRADED_PRICE": 1083.15,
            "CH_PREVIOUS_CLS_PRICE": 1099.65,
            "CH_TOT_TRADED_QTY": 14380396,
            "CH_TOT_TRADED_VAL": 15579539289.95,
            "CH_52WEEK_HIGH_PRICE": 1113.55,
            "CH_52WEEK_LOW_PRICE": 864.4,
            "CH_TOTAL_TRADES": 226080,
            "CH_ISIN": "INE090A01021",
            "createdAt": "2024-04-02T12:00:27.442Z",
            "updatedAt": "2024-04-02T12:00:27.442Z",
            "__v": 0,
            "COP_DELIV_QTY": 7380311,
            "COP_DELIV_PERC": 51.32,
            "VWAP": 1083.39,
            "mTIMESTAMP": "02-Apr-2024"
        },
        {
            "_id": "660d4511d68c6c75db4e9818",
            "CH_SYMBOL": "ICICIBANK",
            "CH_SERIES": "EQ",
            "CH_MARKET_TYPE": "N",
            "CH_TRADE_HIGH_PRICE": 1083.65,
            "CH_TRADE_LOW_PRICE": 1072.25,
            "CH_OPENING_PRICE": 1075,
            "CH_CLOSING_PRICE": 1077.2,
            "CH_LAST_TRADED_PRICE": 1077.35,
            "CH_PREVIOUS_CLS_PRICE": 1081.2,
            "CH_TOT_TRADED_QTY": 15477184,
            "CH_TOT_TRADED_VAL": 16692070515.2,
            "CH_52WEEK_HIGH_PRICE": 1113.55,
            "CH_52WEEK_LOW_PRICE": 864.4,
            "CH_TOTAL_TRADES": 237385,
            "CH_ISIN": "INE090A01021",
            "CH_TIMESTAMP": "2024-04-03",
            "TIMESTAMP": "2024-04-02T18:30:00.000Z",
            "createdAt": "2024-04-03T12:01:21.826Z",
            "updatedAt": "2024-04-03T12:01:21.826Z",
            "__v": 0,
            "COP_DELIV_QTY": 7647513,
            "COP_DELIV_PERC": 49.41,
            "VWAP": 1078.5,
            "mTIMESTAMP": "03-Apr-2024"
        },
        {
            "_id": "660e96854c86b12e15540a0b",
            "CH_SYMBOL": "ICICIBANK",
            "CH_SERIES": "EQ",
            "CH_MARKET_TYPE": "N",
            "CH_TRADE_HIGH_PRICE": 1085.8,
            "CH_TRADE_LOW_PRICE": 1063.45,
            "CH_OPENING_PRICE": 1084.75,
            "CH_CLOSING_PRICE": 1078.85,
            "CH_LAST_TRADED_PRICE": 1080.55,
            "CH_PREVIOUS_CLS_PRICE": 1077.2,
            "CH_TOT_TRADED_QTY": 21419689,
            "CH_TOT_TRADED_VAL": 23015858480.35,
            "CH_52WEEK_HIGH_PRICE": 1113.55,
            "CH_52WEEK_LOW_PRICE": 864.4,
            "CH_TOTAL_TRADES": 405986,
            "CH_ISIN": "INE090A01021",
            "CH_TIMESTAMP": "2024-04-04",
            "TIMESTAMP": "2024-04-03T18:30:00.000Z",
            "createdAt": "2024-04-04T12:01:09.748Z",
            "updatedAt": "2024-04-04T12:01:09.748Z",
            "__v": 0,
            "COP_DELIV_QTY": 8750884,
            "COP_DELIV_PERC": 40.85,
            "VWAP": 1074.52,
            "mTIMESTAMP": "04-Apr-2024"
        },
        {
            "_id": "661017bfb972bf436f411269",
            "CH_SYMBOL": "ICICIBANK",
            "CH_SERIES": "EQ",
            "CH_MARKET_TYPE": "N",
            "CH_TRADE_HIGH_PRICE": 1086,
            "CH_TRADE_LOW_PRICE": 1067.45,
            "CH_OPENING_PRICE": 1070,
            "CH_CLOSING_PRICE": 1083.4,
            "CH_LAST_TRADED_PRICE": 1084,
            "CH_PREVIOUS_CLS_PRICE": 1078.85,
            "CH_TOT_TRADED_QTY": 15340637,
            "CH_TOT_TRADED_VAL": 16470380648.6,
            "CH_52WEEK_HIGH_PRICE": 1113.55,
            "CH_52WEEK_LOW_PRICE": 864.4,
            "CH_TOTAL_TRADES": 208528,
            "CH_ISIN": "INE090A01021",
            "CH_TIMESTAMP": "2024-04-05",
            "TIMESTAMP": "2024-04-04T18:30:00.000Z",
            "createdAt": "2024-04-05T15:24:47.189Z",
            "updatedAt": "2024-04-05T15:24:47.189Z",
            "__v": 0,
            "COP_DELIV_QTY": 10597870,
            "COP_DELIV_PERC": 69.08,
            "VWAP": 1073.64,
            "mTIMESTAMP": "05-Apr-2024"
        },
        {
            "_id": "6613dc7e0e60a36f852fab8e",
            "CH_SYMBOL": "ICICIBANK",
            "CH_SERIES": "EQ",
            "CH_MARKET_TYPE": "N",
            "CH_TIMESTAMP": "2024-04-08",
            "TIMESTAMP": "2024-04-07T18:30:00.000Z",
            "CH_TRADE_HIGH_PRICE": 1091.75,
            "CH_TRADE_LOW_PRICE": 1076.3,
            "CH_OPENING_PRICE": 1078.35,
            "CH_CLOSING_PRICE": 1087.15,
            "CH_LAST_TRADED_PRICE": 1087,
            "CH_PREVIOUS_CLS_PRICE": 1083.4,
            "CH_TOT_TRADED_QTY": 8023461,
            "CH_TOT_TRADED_VAL": 8715249008.2,
            "CH_52WEEK_HIGH_PRICE": 1113.55,
            "CH_52WEEK_LOW_PRICE": 864.4,
            "CH_TOTAL_TRADES": 182575,
            "CH_ISIN": "INE090A01021",
            "createdAt": "2024-04-08T12:01:02.661Z",
            "updatedAt": "2024-04-08T12:01:02.661Z",
            "__v": 0,
            "COP_DELIV_QTY": 5067692,
            "COP_DELIV_PERC": 63.16,
            "VWAP": 1086.22,
            "mTIMESTAMP": "08-Apr-2024"
        },
        {
            "_id": "661551eb5e9189ad01de73a8",
            "CH_SYMBOL": "ICICIBANK",
            "CH_SERIES": "EQ",
            "CH_MARKET_TYPE": "N",
            "CH_TIMESTAMP": "2024-04-09",
            "TIMESTAMP": "2024-04-08T18:30:00.000Z",
            "CH_TRADE_HIGH_PRICE": 1115.25,
            "CH_TRADE_LOW_PRICE": 1088.3,
            "CH_OPENING_PRICE": 1091.95,
            "CH_CLOSING_PRICE": 1107.05,
            "CH_LAST_TRADED_PRICE": 1107.7,
            "CH_PREVIOUS_CLS_PRICE": 1087.15,
            "CH_TOT_TRADED_QTY": 12298463,
            "CH_TOT_TRADED_VAL": 13604116450.75,
            "CH_52WEEK_HIGH_PRICE": 1115.25,
            "CH_52WEEK_LOW_PRICE": 864.4,
            "CH_TOTAL_TRADES": 250588,
            "CH_ISIN": "INE090A01021",
            "createdAt": "2024-04-09T14:34:19.950Z",
            "updatedAt": "2024-04-09T14:34:19.950Z",
            "__v": 0,
            "COP_DELIV_QTY": 6986882,
            "COP_DELIV_PERC": 56.81,
            "VWAP": 1106.16,
            "mTIMESTAMP": "09-Apr-2024"
        },
        {
            "_id": "66167f6e10604a87b12eade9",
            "CH_SYMBOL": "ICICIBANK",
            "CH_SERIES": "EQ",
            "CH_MARKET_TYPE": "N",
            "CH_TRADE_HIGH_PRICE": 1116.55,
            "CH_TRADE_LOW_PRICE": 1105.15,
            "CH_OPENING_PRICE": 1110.95,
            "CH_CLOSING_PRICE": 1109.4,
            "CH_LAST_TRADED_PRICE": 1108.8,
            "CH_PREVIOUS_CLS_PRICE": 1107.05,
            "CH_TOT_TRADED_QTY": 10598000,
            "CH_TOT_TRADED_VAL": 11766295607.5,
            "CH_52WEEK_HIGH_PRICE": 1116.55,
            "CH_52WEEK_LOW_PRICE": 864.4,
            "CH_TOTAL_TRADES": 209324,
            "CH_ISIN": "INE090A01021",
            "CH_TIMESTAMP": "2024-04-10",
            "TIMESTAMP": "2024-04-09T18:30:00.000Z",
            "createdAt": "2024-04-10T12:00:46.775Z",
            "updatedAt": "2024-04-10T12:00:46.775Z",
            "__v": 0,
            "COP_DELIV_QTY": 5038453,
            "COP_DELIV_PERC": 47.54,
            "VWAP": 1110.24,
            "mTIMESTAMP": "10-Apr-2024"
        },
        {
            "_id": "6619225f0661c0c135aaaba0",
            "CH_SYMBOL": "ICICIBANK",
            "CH_SERIES": "EQ",
            "CH_MARKET_TYPE": "N",
            "CH_TIMESTAMP": "2024-04-12",
            "TIMESTAMP": "2024-04-11T18:30:00.000Z",
            "CH_TRADE_HIGH_PRICE": 1111.85,
            "CH_TRADE_LOW_PRICE": 1095.8,
            "CH_OPENING_PRICE": 1103.5,
            "CH_CLOSING_PRICE": 1104.4,
            "CH_LAST_TRADED_PRICE": 1103,
            "CH_PREVIOUS_CLS_PRICE": 1109.4,
            "CH_TOT_TRADED_QTY": 12216657,
            "CH_TOT_TRADED_VAL": 13477844384.65,
            "CH_52WEEK_HIGH_PRICE": 1116.55,
            "CH_52WEEK_LOW_PRICE": 864.4,
            "CH_TOTAL_TRADES": 233873,
            "CH_ISIN": "INE090A01021",
            "createdAt": "2024-04-12T12:00:31.766Z",
            "updatedAt": "2024-04-12T12:00:31.766Z",
            "__v": 0,
            "COP_DELIV_QTY": 5816469,
            "COP_DELIV_PERC": 47.61,
            "VWAP": 1103.24,
            "mTIMESTAMP": "12-Apr-2024"
        },
        {
            "_id": "661d170567f74c7b05bb4218",
            "CH_SYMBOL": "ICICIBANK",
            "CH_SERIES": "EQ",
            "CH_MARKET_TYPE": "N",
            "CH_TRADE_HIGH_PRICE": 1106.15,
            "CH_TRADE_LOW_PRICE": 1076.6,
            "CH_OPENING_PRICE": 1100.2,
            "CH_CLOSING_PRICE": 1078.35,
            "CH_LAST_TRADED_PRICE": 1077.6,
            "CH_PREVIOUS_CLS_PRICE": 1104.4,
            "CH_TOT_TRADED_QTY": 10526597,
            "CH_TOT_TRADED_VAL": 11426239543,
            "CH_52WEEK_HIGH_PRICE": 1116.55,
            "CH_52WEEK_LOW_PRICE": 882.4,
            "CH_TOTAL_TRADES": 276339,
            "CH_ISIN": "INE090A01021",
            "CH_TIMESTAMP": "2024-04-15",
            "TIMESTAMP": "2024-04-14T18:30:00.000Z",
            "createdAt": "2024-04-15T12:01:09.359Z",
            "updatedAt": "2024-04-15T12:01:09.359Z",
            "__v": 0,
            "COP_DELIV_QTY": 6130101,
            "COP_DELIV_PERC": 58.23,
            "VWAP": 1085.46,
            "mTIMESTAMP": "15-Apr-2024"
        },
        {
            "_id": "661e687ec1cb1b138131f555",
            "CH_SYMBOL": "ICICIBANK",
            "CH_SERIES": "EQ",
            "CH_MARKET_TYPE": "N",
            "CH_TIMESTAMP": "2024-04-16",
            "TIMESTAMP": "2024-04-15T18:30:00.000Z",
            "CH_TRADE_HIGH_PRICE": 1074.6,
            "CH_TRADE_LOW_PRICE": 1062.7,
            "CH_OPENING_PRICE": 1070.55,
            "CH_CLOSING_PRICE": 1067.05,
            "CH_LAST_TRADED_PRICE": 1068.75,
            "CH_PREVIOUS_CLS_PRICE": 1078.35,
            "CH_TOT_TRADED_QTY": 11278092,
            "CH_TOT_TRADED_VAL": 12039721950.35,
            "CH_52WEEK_HIGH_PRICE": 1116.55,
            "CH_52WEEK_LOW_PRICE": 882.4,
            "CH_TOTAL_TRADES": 245846,
            "CH_ISIN": "INE090A01021",
            "createdAt": "2024-04-16T12:01:02.312Z",
            "updatedAt": "2024-04-16T12:01:02.312Z",
            "__v": 0,
            "COP_DELIV_QTY": 7147384,
            "COP_DELIV_PERC": 63.37,
            "VWAP": 1067.53,
            "mTIMESTAMP": "16-Apr-2024"
        },
        {
            "_id": "66210b91e76a74aef2218919",
            "CH_SYMBOL": "ICICIBANK",
            "CH_SERIES": "EQ",
            "CH_MARKET_TYPE": "N",
            "CH_TRADE_HIGH_PRICE": 1078.05,
            "CH_TRADE_LOW_PRICE": 1050.45,
            "CH_OPENING_PRICE": 1074,
            "CH_CLOSING_PRICE": 1055.45,
            "CH_LAST_TRADED_PRICE": 1055.3,
            "CH_PREVIOUS_CLS_PRICE": 1067.05,
            "CH_TOT_TRADED_QTY": 16564216,
            "CH_TOT_TRADED_VAL": 17575027387.85,
            "CH_52WEEK_HIGH_PRICE": 1116.55,
            "CH_52WEEK_LOW_PRICE": 882.4,
            "CH_TOTAL_TRADES": 256438,
            "CH_ISIN": "INE090A01021",
            "CH_TIMESTAMP": "2024-04-18",
            "TIMESTAMP": "2024-04-17T18:30:00.000Z",
            "createdAt": "2024-04-18T12:01:21.838Z",
            "updatedAt": "2024-04-18T12:01:21.838Z",
            "__v": 0,
            "COP_DELIV_QTY": 9592696,
            "COP_DELIV_PERC": 57.91,
            "VWAP": 1061.02,
            "mTIMESTAMP": "18-Apr-2024"
        },
        {
            "_id": "66225cfe337be0542c00914b",
            "CH_SYMBOL": "ICICIBANK",
            "CH_SERIES": "EQ",
            "CH_MARKET_TYPE": "N",
            "CH_TIMESTAMP": "2024-04-19",
            "TIMESTAMP": "2024-04-18T18:30:00.000Z",
            "CH_TRADE_HIGH_PRICE": 1072,
            "CH_TRADE_LOW_PRICE": 1048.1,
            "CH_OPENING_PRICE": 1052.95,
            "CH_CLOSING_PRICE": 1067.25,
            "CH_LAST_TRADED_PRICE": 1068,
            "CH_PREVIOUS_CLS_PRICE": 1055.45,
            "CH_TOT_TRADED_QTY": 11284433,
            "CH_TOT_TRADED_VAL": 11984483579.2,
            "CH_52WEEK_HIGH_PRICE": 1116.55,
            "CH_52WEEK_LOW_PRICE": 882.4,
            "CH_TOTAL_TRADES": 226385,
            "CH_ISIN": "INE090A01021",
            "createdAt": "2024-04-19T12:01:02.810Z",
            "updatedAt": "2024-04-19T12:01:02.810Z",
            "__v": 0,
            "COP_DELIV_QTY": 5943916,
            "COP_DELIV_PERC": 52.67,
            "VWAP": 1062.04,
            "mTIMESTAMP": "19-Apr-2024"
        },
        {
            "_id": "66266b2a8b80d02869c4b3ea",
            "CH_SYMBOL": "ICICIBANK",
            "CH_SERIES": "EQ",
            "CH_MARKET_TYPE": "N",
            "CH_TRADE_HIGH_PRICE": 1088.7,
            "CH_TRADE_LOW_PRICE": 1070.35,
            "CH_OPENING_PRICE": 1078.8,
            "CH_CLOSING_PRICE": 1086.65,
            "CH_LAST_TRADED_PRICE": 1087.45,
            "CH_PREVIOUS_CLS_PRICE": 1067.25,
            "CH_TOT_TRADED_QTY": 10346714,
            "CH_TOT_TRADED_VAL": 11185892977.85,
            "CH_52WEEK_HIGH_PRICE": 1116.55,
            "CH_52WEEK_LOW_PRICE": 895,
            "CH_TOTAL_TRADES": 233249,
            "CH_ISIN": "INE090A01021",
            "CH_TIMESTAMP": "2024-04-22",
            "TIMESTAMP": "2024-04-21T18:30:00.000Z",
            "createdAt": "2024-04-22T13:50:34.078Z",
            "updatedAt": "2024-04-22T13:50:34.078Z",
            "__v": 0,
            "COP_DELIV_QTY": 6324415,
            "COP_DELIV_PERC": 61.12,
            "VWAP": 1081.11,
            "mTIMESTAMP": "22-Apr-2024"
        }
    ],
    "meta": {
        "series": "ALL",
        "fromDate": "09-01-2024",
        "toDate": "08-01-2025",
        "symbols": [
            "ICICIBANK",
            "ICICIBANK"
        ]
    }
}